pbumongo/__init__.py
pbumongo/job_progress.py
pbumongo/mongo_connection.py
pbumongo/mongo_document.py
pbumongo/mongo_store.py
pbumongo-1.2.0.dist-info/LICENSE
pbumongo-1.2.0.dist-info/METADATA
pbumongo-1.2.0.dist-info/WHEEL
pbumongo-1.2.0.dist-info/top_level.txt
pbumongo-1.2.0.dist-info/RECORD
