Metadata-Version: 2.1
Name: pbumongo
Version: 1.2.0
Summary: Basic MongoDB wrapper for object-oriented collection handling
Home-page: https://github.com/ilfrich/pbu-mongo
Author: Peter Ilfrich
Author-email: das-peter@gmx.de
License: Apache-2.0
License-File: LICENSE
Requires-Dist: pymongo ==3.11.2
Requires-Dist: pbu >=1.1.5
